pythonvideoannotator/__init__.py
pythonvideoannotator/__main__.py
pythonvideoannotator/settings.py
pythonvideoannotator/userstats.py
pythonvideoannotator/base_module/__init__.py
pythonvideoannotator/base_module/base.py
pythonvideoannotator/base_module/base_io.py
pythonvideoannotator/base_module/base_keys_events.py
pythonvideoannotator/resources/__init__.py
pythonvideoannotator/resources/icons/acceleration.png
pythonvideoannotator/resources/icons/add.png
pythonvideoannotator/resources/icons/angle.png
pythonvideoannotator/resources/icons/area.png
pythonvideoannotator/resources/icons/aspect-ratio.png
pythonvideoannotator/resources/icons/background.png
pythonvideoannotator/resources/icons/black-circle.png
pythonvideoannotator/resources/icons/circle.png
pythonvideoannotator/resources/icons/color-component.png
pythonvideoannotator/resources/icons/colors.png
pythonvideoannotator/resources/icons/contour.png
pythonvideoannotator/resources/icons/datasets.png
pythonvideoannotator/resources/icons/delete-path.png
pythonvideoannotator/resources/icons/delete.png
pythonvideoannotator/resources/icons/distances.png
pythonvideoannotator/resources/icons/duplicate.png
pythonvideoannotator/resources/icons/edit.png
pythonvideoannotator/resources/icons/ellipse.png
pythonvideoannotator/resources/icons/exit.png
pythonvideoannotator/resources/icons/export.png
pythonvideoannotator/resources/icons/geometry.png
pythonvideoannotator/resources/icons/height.png
pythonvideoannotator/resources/icons/hull.png
pythonvideoannotator/resources/icons/image.png
pythonvideoannotator/resources/icons/import.png
pythonvideoannotator/resources/icons/info.png
pythonvideoannotator/resources/icons/interpolate.png
pythonvideoannotator/resources/icons/link.png
pythonvideoannotator/resources/icons/mark-place.png
pythonvideoannotator/resources/icons/motion.png
pythonvideoannotator/resources/icons/movie.png
pythonvideoannotator/resources/icons/movies.png
pythonvideoannotator/resources/icons/new.png
Python_video_annotator-3.306.dist-info/METADATA
Python_video_annotator-3.306.dist-info/WHEEL
Python_video_annotator-3.306.dist-info/entry_points.txt
Python_video_annotator-3.306.dist-info/top_level.txt
Python_video_annotator-3.306.dist-info/RECORD
