Metadata-Version: 2.1
Name: Python-video-annotator
Version: 3.306
Summary: UNKNOWN
Home-page: https://bitbucket.org/fchampalimaud/pythonvideoannotator-models
Author: ['Ricardo Ribeiro']
Author-email: ricardojvr@gmail.com
License: UNKNOWN
Platform: UNKNOWN
Requires-Dist: simplejson
Requires-Dist: pypi-xmlrpc
Requires-Dist: send2trash
Requires-Dist: scipy
Requires-Dist: sklearn
Requires-Dist: confapp
Requires-Dist: geometry-designer (==0.4.38)
Requires-Dist: modular-computer-vision-api-gui (==0.3.31)
Requires-Dist: pyforms-gui (==4.904.152)
Requires-Dist: modular-computer-vision-api (==0.3.29)
Requires-Dist: python-video-annotator-models-gui (==0.7.63)
Requires-Dist: python-video-annotator-models (==0.8.82)
Requires-Dist: python-video-annotator-module-timeline (==0.6.26)
Requires-Dist: python-video-annotator-module-eventstats (==0.5.15)
Requires-Dist: python-video-annotator-module-virtual-object-generator (==0.6.26)
Requires-Dist: python-video-annotator-module-deeplab (==0.902.21)
Requires-Dist: python-video-annotator-module-contours-images (==0.5.28)
Requires-Dist: python-video-annotator-module-tracking (==0.6.38)
Requires-Dist: python-video-annotator-module-smooth-paths (==0.5.19)
Requires-Dist: python-video-annotator-module-distances (==0.5.18)
Requires-Dist: python-video-annotator-module-path-map (==0.6.16)
Requires-Dist: python-video-annotator-module-motion-counter (==0.5.26)
Requires-Dist: python-video-annotator-module-create-paths (==0.5.15)
Requires-Dist: python-video-annotator-module-regions-filter (==0.5.18)
Requires-Dist: python-video-annotator-module-import-export (==0.5.23)
Requires-Dist: python-video-annotator-module-background-finder (==0.5.21)
Requires-Dist: python-video-annotator-module-find-orientation (==0.5.18)
Requires-Dist: python-video-annotator-module-path-editor (==0.5.28)
